dokuwiki_autodoc/__about__.py
dokuwiki_autodoc/__init__.py
dokuwiki_autodoc/autodoc.py
dokuwiki_autodoc/liquid_filters.py
dokuwiki_autodoc/unified_measurement_adapter.py
dokuwiki_autodoc/templates/__init__.py
dokuwiki_autodoc/templates/doc_base.txt.liquid
dokuwiki_autodoc/templates/sample.txt.liquid
dokuwiki_autodoc/templates/unified_exp_base.txt.liquid
dokuwiki_autodoc-1.6.2.dist-info/METADATA
dokuwiki_autodoc-1.6.2.dist-info/WHEEL
dokuwiki_autodoc-1.6.2.dist-info/licenses/LICENSE.txt
dokuwiki_autodoc-1.6.2.dist-info/RECORD
