Metadata-Version: 2.4
Name: dokuwiki-autodoc
Version: 1.6.2
Summary: Automatically generate documentation in Dokuwiki
Project-URL: Homepage, https://github.com/qkitgroup/dokuwiki-autodoc
Project-URL: Bug Tracker, https://github.com/qkitgroup/dokuwiki-autodoc/issues
Author: PHI AG Ustinov
License-Expression: GPL-2.0-or-later
License-File: LICENSE.txt
Keywords: dokuwiki,qkit
Classifier: Development Status :: 4 - Beta
Classifier: Framework :: Jupyter :: JupyterLab :: 3
Classifier: Intended Audience :: Science/Research
Classifier: License :: OSI Approved :: GNU General Public License v2 (GPLv2)
Classifier: Programming Language :: Python
Classifier: Programming Language :: Python :: 3.7
Classifier: Programming Language :: Python :: 3.8
Classifier: Programming Language :: Python :: 3.9
Classifier: Programming Language :: Python :: 3.10
Classifier: Programming Language :: Python :: 3.11
Classifier: Programming Language :: Python :: Implementation :: CPython
Classifier: Programming Language :: Python :: Implementation :: PyPy
Requires-Python: >=3.7
Requires-Dist: dokuwiki>=1.3.3
Requires-Dist: importlib-resources
Requires-Dist: numpy
Requires-Dist: python-liquid>=2.0.0
Provides-Extra: certifi
Requires-Dist: certifi; extra == 'certifi'
